Workbook

Sheet Week Apr 16-22
A1: Income Statement
A3: Revenue/Expenses | B3: Week | C3: YTD | D3: Notes
A5: POSTUP
A6: Wagerweb Income | B6: 2766 | C6: 2766
A7: SBO Income | B7: 9762 | C7: 9762 | D7: Affiliate Commissions
A8: Handicapper Income | B8: 0 | C8: 0
A9: Payroll Postup | B9: =-344-174-183-200-260-483-375-250-250-1000-750-222-364-300-375-400-250-250-250-250-250-750 -> -7930 | C9: =-344-174-183-200-260-483-375-250-250-1000-750-222-364-300-375-400-250-250-250-250-250-750 -> -7930
A10: Sales Commissions | B10: -115 | C10: -115
A11: Caja | B11: =-16800/52 -> -323.07692 | C11: =-16800/52 -> -323.07692 | D11: $16,800 a year average
A12: Office PerHead.com | B12: =-(25000*12)/52/2 -> -2884.6154 | C12: =-(25000*12)/52/2 -> -2884.6154 | D12: $300,000 a year
A13: Bacons | B13: =-4820/52 -> -92.692308 | C13: =-4820/52 -> -92.692308 | D13: $4,820 a year
A14: Sports Direct | B14: =-12000/52 -> -230.76923 | C14: =-12000/52 -> -230.76923 | D14: $12,000 a year
A15: Copywright | B15: =-24000/52 -> -461.53846 | C15: -500 | D15: $24,000 a year
A16: Bronto | B16: =-8200/52 -> -157.69231 | C16: =-8200/52 -> -157.69231 | D16: $8,200 a year
A17: Supplies | B17: 0 | C17: 0 | D17: Variable
A18: POSTUP TOTAL | B18: =SUM(B6:B17) -> 332.61538 | C18: =SUM(C6:C17) -> 294.15385
A20: CREDIT/PPH | D20: PERCENTAGES
A21: 007B | B21: 18751 | C21: 18751 | D21: 1
A22: 007Kenny | B22: =-53*0.25 -> -13.25 | C22: =-53*0.25 -> -13.25 | D22: 0.25
A23: 700A | B23: =2304*0.5 -> 1152 | C23: =2304*0.5 -> 1152 | D23: 0.5
A24: 700B | B24: =-2416*0.25 -> -604 | C24: =-2416*0.25 -> -604 | D24: 0.25
A25: Zorba | B25: 11372 | C25: 11372 | D25: 0.375
A26: Pineapple | B26: 36792 | C26: 36792 | D26: 0.5
A27: Allen PPH | B27: 0 | C27: 0
A28: Lante PPH | B28: 0 | C28: 0
A29: Fl Scott PPH | B29: 0 | C29: 0
A30: Billy M PPH | B30: 0 | C30: 0
A31: Sphynx PPH | B31: 0 | C31: 0
A32: Office Perhead.com | B32: =-(25000*12)/52/2 -> -2884.6154 | C32: =-(25000*12)/52/2 -> -2884.6154 | D32: $300,000 a year
A33: Payroll PPH | B33: 0 | C33: 0
A34: Supplies | B34: 0 | C34: 0
A35: CREDIT/PPH TOTAL | B35: =SUM(B21:B34) -> 64565.135 | C35: =SUM(C21:C34) -> 64565.135
A37: PROCESSING
A38: Fees Income | B38: 2318.91 | C38: 2318.91
A39: Payroll Processing | B39: =-146-300-500 -> -946 | C39: =-146-300-500 -> -946 | D39: Paola, Cindy and Silvia
A40: Office Rent | B40: =-15600/52/2 -> -150 | C40: =-15600/52/2 -> -150 | D40: $15,600 a year
A41: Electricity | B41: 0 | C41: 0 | D41: Variable
A42: Water | B42: 0 | C42: 0 | D42: Variable
A43: Supplies | B43: 0 | C43: 0 | D43: Variable
A44: Maid | B44: -50 | C44: -50 | D44: $100 a week
A45: PROCESSING TOTAL | B45: =SUM(B38:B44)*0.75 -> 879.6825 | C45: =SUM(C38:C44)*0.75 -> 879.6825
A47: BETTING
A48: Betting Income | B48: 1833 | C48: 1833
A49: Payroll Gambling | B49: =-625 -> -625 | C49: =-625 -> -625 | D49: Willy
A50: Office Rent | B50: =-15600/52/2 -> -150 | C50: =-15600/52/2 -> -150 | D50: $15,600 a year
A51: Electricity | B51: 0 | C51: 0 | D51: Variable
A52: Water | B52: 0 | C52: 0 | D52: Variable
A53: Supplies | B53: 0 | C53: 0 | D53: Variable
A54: Maid | B54: -50 | C54: -50 | D54: $100 a week
A55: California Server | B55: =-962/52 -> -18.5 | C55: =-962/52 -> -18.5 | D55: $960 a year
A56: BETTING TOTAL | B56: =SUM(B48:B55) -> 989.5 | C56: =SUM(C48:C55) -> 989.5
A58: OVERALL PROFIT/LOSS | B58: =B18+B35+B45+B56 -> 66766.932 | C58: =C18+C35+C45+C56 -> 66728.471
A61: Michael | B61: =(B18+B35+B45)*0.6+(B56)*0.45 -> 39911.734 | C61: =B61 -> 39911.734 | D61: 60%-45%
A62: Kevin | B62: =(B18+B35+B45)*0.2+(B56)*0.2 -> 13353.386 | C62: =B62 -> 13353.386 | D62: 20%-20%
A63: Frank | B63: =(B18+B35+B45)*0.2+(B56)*0.2 -> 13353.386 | C63: =B63 -> 13353.386 | D63: 20%-20%
A64: Seal | B64: =B56*0.15 -> 148.425 | C64: =B64 -> 148.425 | D64: 0%-15%

Sheet Week Apr 23-29
A1: Income Statement
A3: Revenue/Expenses | B3: Week | C3: YTD | D3: Notes
A5: POSTUP
A6: Wagerweb Income | B6: 6843.91 | C6: =B6+'Week Apr 16-22'!C6 -> 9609.91
A7: SBO Income | B7: 1871 | C7: =B7+'Week Apr 16-22'!C7 -> 11633 | D7: Affiliate Commissions
A8: Handicapper Income | B8: 29.99 | C8: =B8+'Week Apr 16-22'!C8 -> 29.99
A9: Payroll Postup | B9: =-344-174-170-200-260-483-375-250-250-1000-750-222-364-300-375-400-250-209-250-250-250-750 -> -7876 | C9: =B9+'Week Apr 16-22'!C9 -> -15806
A10: Sales Commissions | B10: 0 | C10: =B10+'Week Apr 16-22'!C10 -> -115
A11: Caja | B11: =-16800/52 -> -323.07692 | C11: =B11+'Week Apr 16-22'!C11 -> -646.15385 | D11: $16,800 a year average
A12: Office PerHead.com | B12: =-(25000*12)/52/2 -> -2884.6154 | C12: =B12+'Week Apr 16-22'!C12 -> -5769.2308 | D12: $300,000 a year
A13: Bacons | B13: =-4820/52 -> -92.692308 | C13: =B13+'Week Apr 16-22'!C13 -> -185.38462 | D13: $4,820 a year
A14: Sports Direct | B14: =-12000/52 -> -230.76923 | C14: =B14+'Week Apr 16-22'!C14 -> -461.53846 | D14: $12,000 a year
A15: Copywright | B15: =-24000/52 -> -461.53846 | C15: =B15+'Week Apr 16-22'!C15 -> -961.53846 | D15: $24,000 a year
A16: Bronto | B16: =-8200/52 -> -157.69231 | C16: =B16+'Week Apr 16-22'!C16 -> -315.38462 | D16: $8,200 a year
A17: Supplies | B17: 0 | C17: =B17+'Week Apr 16-22'!C17 -> 0 | D17: Variable
A18: POSTUP TOTAL | B18: =SUM(B6:B17) -> -3281.4846 | C18: =B18+'Week Apr 16-22'!C18 -> -2987.3308
A20: CREDIT/PPH | D20: PERCENTAGES
A21: 007B | B21: 11440 | C21: =B21+'Week Apr 16-22'!C21 -> 30191 | D21: 1
A22: 007Kenny | B22: -10 | C22: =B22+'Week Apr 16-22'!C22 -> -23.25 | D22: 0.25
A23: 700A | B23: -2672.5 | C23: =B23+'Week Apr 16-22'!C23 -> -1520.5 | D23: 0.5
A24: 700B | B24: -995 | C24: =B24+'Week Apr 16-22'!C24 -> -1599 | D24: 0.25
A25: Zorba | B25: -3292 | C25: =B25+'Week Apr 16-22'!C25 -> 8080 | D25: 0.375
A26: Pineapple | B26: -13553 | C26: =B26+'Week Apr 16-22'!C26 -> 23239 | D26: 0.5
A27: Allen PPH | B27: 0 | C27: =B27+'Week Apr 16-22'!C27 -> 0
A28: Lante PPH | B28: 0 | C28: =B28+'Week Apr 16-22'!C28 -> 0
A29: Fl Scott PPH | B29: 0 | C29: =B29+'Week Apr 16-22'!C29 -> 0
A30: Billy M PPH | B30: 0 | C30: =B30+'Week Apr 16-22'!C30 -> 0
A31: Sphynx PPH | B31: 0 | C31: =B31+'Week Apr 16-22'!C31 -> 0
A32: Office Perhead.com | B32: =-(25000*12)/52/2 -> -2884.6154 | C32: =B32+'Week Apr 16-22'!C32 -> -5769.2308 | D32: $300,000 a year
A33: Payroll PPH | B33: 0 | C33: =B33+'Week Apr 16-22'!C33 -> 0
A34: Supplies | B34: 0 | C34: =B34+'Week Apr 16-22'!C34 -> 0
A35: CREDIT/PPH TOTAL | B35: =SUM(B21:B34) -> -11967.115 | C35: =B35+'Week Apr 16-22'!C35 -> 52598.019
A37: PROCESSING
A38: Fees Income | B38: 2293.26 | C38: =B38+'Week Apr 16-22'!C38 -> 4612.17
A39: Payroll Processing | B39: =-150-300-500 -> -950 | C39: =B39+'Week Apr 16-22'!C39 -> -1896 | D39: Paola, Cindy and Silvia
A40: Office Rent | B40: =-15600/52/2 -> -150 | C40: =B40+'Week Apr 16-22'!C40 -> -300 | D40: $15,600 a year
A41: Electricity | B41: 0 | C41: =B41+'Week Apr 16-22'!C41 -> 0 | D41: Variable
A42: Water | B42: 0 | C42: =B42+'Week Apr 16-22'!C42 -> 0 | D42: Variable
A43: Supplies | B43: 0 | C43: =B43+'Week Apr 16-22'!C43 -> 0 | D43: Variable
A44: Maid | B44: -50 | C44: =B44+'Week Apr 16-22'!C44 -> -100 | D44: $100 a week
A45: PROCESSING TOTAL | B45: =SUM(B38:B44)*0.75 -> 857.445 | C45: =B45+'Week Apr 16-22'!C45 -> 1737.1275
A47: BETTING
A48: Betting Income | B48: 49135 | C48: =B48+'Week Apr 16-22'!C48 -> 50968
A49: Payroll Gambling | B49: =-625 -> -625 | C49: =B49+'Week Apr 16-22'!C49 -> -1250 | D49: Willy
A50: Office Rent | B50: =-15600/52/2 -> -150 | C50: =B50+'Week Apr 16-22'!C50 -> -300 | D50: $15,600 a year
A51: Electricity | B51: 0 | C51: =B51+'Week Apr 16-22'!C51 -> 0 | D51: Variable
A52: Water | B52: 0 | C52: =B52+'Week Apr 16-22'!C52 -> 0 | D52: Variable
A53: Supplies | B53: 0 | C53: =B53+'Week Apr 16-22'!C53 -> 0 | D53: Variable
A54: Maid | B54: -50 | C54: =B54+'Week Apr 16-22'!C54 -> -100 | D54: $100 a week
A55: California Server | B55: =-962/52 -> -18.5 | C55: =B55+'Week Apr 16-22'!C55 -> -37 | D55: $960 a year
A56: BETTING TOTAL | B56: =SUM(B48:B55) -> 48291.5 | C56: =B56+'Week Apr 16-22'!C56 -> 49281
A58: OVERALL PROFIT/LOSS | B58: =B18+B35+B45+B56 -> 33900.345 | C58: =B58+'Week Apr 16-22'!C58 -> 100628.82
A61: Michael | B61: =(B18+B35+B45)*0.6+(B56)*0.45 -> 13096.482 | C61: =B61+'Week Apr 16-22'!C61 -> 53008.216 | D61: 60%-45%
A62: Kevin | B62: =(B18+B35+B45)*0.2+(B56)*0.2 -> 6780.069 | C62: =B62+'Week Apr 16-22'!C62 -> 20133.456 | D62: 20%-20%
A63: Frank | B63: =(B18+B35+B45)*0.2+(B56)*0.2 -> 6780.069 | C63: =B63+'Week Apr 16-22'!C63 -> 20133.456 | D63: 20%-20%
A64: Seal | B64: =B56*0.15 -> 7243.725 | C64: =B64+'Week Apr 16-22'!C64 -> 7392.15 | D64: 0%-15%

Sheet Week Apr 30-6
A1: Income Statement
A3: Revenue/Expenses | B3: Week | C3: YTD | D3: Notes
A5: POSTUP
A6: Wagerweb Income | B6: 4483 | C6: =B6+'Week Apr 23-29'!C6 -> 14092.91
A7: SBO Income | B7: 6240 | C7: =B7+'Week Apr 23-29'!C7 -> 17873 | D7: Affiliate Commissions
A8: Handicapper Income | B8: =29.99*2 -> 59.98 | C8: =B8+'Week Apr 23-29'!C8 -> 89.97
A9: Payroll Postup | B9: =-344-174-170-200-260-483-375-250-250-1000-750-222-364-300-375-400-250-209-250-250-250-750 -> -7876 | C9: =B9+'Week Apr 23-29'!C9 -> -23682
A10: Sales Commissions | B10: -85 | C10: =B10+'Week Apr 23-29'!C10 -> -200
A11: Caja | B11: =-16800/52 -> -323.07692 | C11: =B11+'Week Apr 23-29'!C11 -> -969.23077 | D11: $16,800 a year average
A12: Office PerHead.com | B12: =-(25000*12)/52/2 -> -2884.6154 | C12: =B12+'Week Apr 23-29'!C12 -> -8653.8462 | D12: $300,000 a year
A13: Bacons | B13: =-4820/52 -> -92.692308 | C13: =B13+'Week Apr 23-29'!C13 -> -278.07692 | D13: $4,820 a year
A14: Sports Direct | B14: =-12000/52 -> -230.76923 | C14: =B14+'Week Apr 23-29'!C14 -> -692.30769 | D14: $12,000 a year
A15: Copywright | B15: =-24000/52 -> -461.53846 | C15: =B15+'Week Apr 23-29'!C15 -> -1423.0769 | D15: $24,000 a year
A16: Bronto | B16: =-8200/52 -> -157.69231 | C16: =B16+'Week Apr 23-29'!C16 -> -473.07692 | D16: $8,200 a year
A17: Supplies | B17: 0 | C17: =B17+'Week Apr 23-29'!C17 -> 0 | D17: Variable
A18: POSTUP TOTAL | B18: =SUM(B6:B17) -> -1328.4046 | C18: =B18+'Week Apr 23-29'!C18 -> -4315.7354
A20: CREDIT/PPH | D20: PERCENTAGES
A21: 007B | B21: 24567 | C21: =B21+'Week Apr 23-29'!C21 -> 54758 | D21: 1
A22: 007Kenny | B22: =257*0.25 -> 64.25 | C22: =B22+'Week Apr 23-29'!C22 -> 41 | D22: 0.25
A23: 700A | B23: =7247*0.5 -> 3623.5 | C23: =B23+'Week Apr 23-29'!C23 -> 2103 | D23: 0.5
A24: 700B | B24: =10486*0.25 -> 2621.5 | C24: =B24+'Week Apr 23-29'!C24 -> 1022.5 | D24: 0.25
A25: Zorba | B25: -5696 | C25: =B25+'Week Apr 23-29'!C25 -> 2384 | D25: 0.375
A26: Pineapple | B26: 24764 | C26: =B26+'Week Apr 23-29'!C26 -> 48003 | D26: 0.5
A27: Allen PPH | B27: 0 | C27: =B27+'Week Apr 23-29'!C27 -> 0
A28: Lante PPH | B28: 0 | C28: =B28+'Week Apr 23-29'!C28 -> 0
A29: Fl Scott PPH | B29: 0 | C29: =B29+'Week Apr 23-29'!C29 -> 0
A30: Billy M PPH | B30: 0 | C30: =B30+'Week Apr 23-29'!C30 -> 0
A31: Sphynx PPH | B31: 0 | C31: =B31+'Week Apr 23-29'!C31 -> 0
A32: Office Perhead.com | B32: =-(25000*12)/52/2 -> -2884.6154 | C32: =B32+'Week Apr 23-29'!C32 -> -8653.8462 | D32: $300,000 a year
A33: Payroll PPH | B33: 0 | C33: =B33+'Week Apr 23-29'!C33 -> 0
A34: Supplies | B34: 0 | C34: =B34+'Week Apr 23-29'!C34 -> 0
A35: CREDIT/PPH TOTAL | B35: =SUM(B21:B34) -> 47059.635 | C35: =B35+'Week Apr 23-29'!C35 -> 99657.654
A37: PROCESSING
A38: Fees Income | B38: 1552.76 | C38: =B38+'Week Apr 23-29'!C38 -> 6164.93
A39: Payroll Processing | B39: =-150-500-300 -> -950 | C39: =B39+'Week Apr 23-29'!C39 -> -2846 | D39: Paola, Cindy and Silvia
A40: Office Rent | B40: =-15600/52/2 -> -150 | C40: =B40+'Week Apr 23-29'!C40 -> -450 | D40: $15,600 a year
A41: Electricity | B41: 0 | C41: =B41+'Week Apr 23-29'!C41 -> 0 | D41: Variable
A42: Water | B42: 0 | C42: =B42+'Week Apr 23-29'!C42 -> 0 | D42: Variable
A43: Supplies | B43: =-15/2 -> -7.5 | C43: =B43+'Week Apr 23-29'!C43 -> -7.5 | D43: Variable
A44: Maid | B44: =-100/2 -> -50 | C44: =B44+'Week Apr 23-29'!C44 -> -150 | D44: $100 a week
A45: PROCESSING TOTAL | B45: =SUM(B38:B44)*0.75 -> 296.445 | C45: =B45+'Week Apr 23-29'!C45 -> 2033.5725
A47: BETTING
A48: Betting Income | B48: 61542 | C48: =B48+'Week Apr 23-29'!C48 -> 112510
A49: Payroll Gambling | B49: =-625 -> -625 | C49: =B49+'Week Apr 23-29'!C49 -> -1875 | D49: Willy
A50: Office Rent | B50: =-15600/52/2 -> -150 | C50: =B50+'Week Apr 23-29'!C50 -> -450 | D50: $15,600 a year
A51: Electricity | B51: 0 | C51: =B51+'Week Apr 23-29'!C51 -> 0 | D51: Variable
A52: Water | B52: 0 | C52: =B52+'Week Apr 23-29'!C52 -> 0 | D52: Variable
A53: Supplies | B53: =-15/2 -> -7.5 | C53: =B53+'Week Apr 23-29'!C53 -> -7.5 | D53: Variable
A54: Maid | B54: =-100/2 -> -50 | C54: =B54+'Week Apr 23-29'!C54 -> -150 | D54: $100 a week
A55: California Server | B55: =-962/52 -> -18.5 | C55: =B55+'Week Apr 23-29'!C55 -> -55.5 | D55: $960 a year
A56: BETTING TOTAL | B56: =SUM(B48:B55) -> 60691 | C56: =B56+'Week Apr 23-29'!C56 -> 109972
A58: OVERALL PROFIT/LOSS | B58: =B18+B35+B45+B56 -> 106718.68 | C58: =B58+'Week Apr 23-29'!C58 -> 207347.49
A61: Michael | B61: =(B18+B35+B45)*0.6+(B56)*0.45 -> 54927.555 | C61: =B61+'Week Apr 23-29'!C61 -> 107935.77 | D61: 60%-45%
A62: Kevin | B62: =(B18+B35+B45)*0.2+(B56)*0.2 -> 21343.735 | C62: =B62+'Week Apr 23-29'!C62 -> 41477.19 | D62: 20%-20%
A63: Frank | B63: =(B18+B35+B45)*0.2+(B56)*0.2 -> 21343.735 | C63: =B63+'Week Apr 23-29'!C63 -> 41477.19 | D63: 20%-20%
A64: Seal | B64: =B56*0.15 -> 9103.65 | C64: =B64+'Week Apr 23-29'!C64 -> 16495.8 | D64: 0%-15%
